aws_administrator/__init__.py
aws_administrator/__init__.pyi
aws_administrator/__main__.py
aws_administrator/__main__.pyi
aws_administrator/aws_actions_get.py
aws_administrator/aws_actions_get.pyi
aws_administrator/aws_s3_getbuckets.py
aws_administrator/aws_s3_getbuckets.pyi
aws_administrator/aws_sgs_get.py
aws_administrator/aws_sgs_get.pyi
aws_administrator/aws_sso_assign.py
aws_administrator/aws_sso_assign.pyi
aws_administrator/aws_sso_get.py
aws_administrator/aws_sso_get.pyi
aws_administrator/aws_sso_json.py
aws_administrator/aws_sso_json.pyi
aws_administrator/aws_sso_mappings.py
aws_administrator/aws_sso_mappings.pyi
aws_administrator/aws_sso_memberships.py
aws_administrator/aws_sso_memberships.pyi
aws_administrator/aws_sso_update.py
aws_administrator/aws_sso_update.pyi
aws_administrator/aws_vpc_getvpcs.py
aws_administrator/aws_vpc_getvpcs.pyi
aws_administrator/extras/parameters.ini
aws_administrator/helper_aws_ec2.py
aws_administrator/helper_aws_ec2.pyi
aws_administrator/helper_aws_entrypoint.py
aws_administrator/helper_aws_entrypoint.pyi
aws_administrator/helper_aws_iam.py
aws_administrator/helper_aws_iam.pyi
aws_administrator/helper_aws_s3.py
aws_administrator/helper_aws_s3.pyi
aws_administrator/helper_aws_sso.py
aws_administrator/helper_aws_sso.pyi
aws_administrator/helper_common.py
aws_administrator/helper_common.pyi
aws_administrator/helper_parameters.py
aws_administrator/helper_parameters.pyi
aws_administrator/py.typed
aws_administrator-2.4.4.dist-info/METADATA
aws_administrator-2.4.4.dist-info/WHEEL
aws_administrator-2.4.4.dist-info/RECORD
