Metadata-Version: 2.1
Name: aws_administrator
Version: 2.4.4
Summary: Run AWS administrative scripts.
Home-page: https://gitlab.com/fer1035_python/modules/pypi-aws_administrator
License: GPL-2.0-only
Keywords: aws,administrator,helper,scripts
Author: Ahmad Ferdaus Abd Razak
Author-email: fer1035@gmail.com
Requires-Python: >=3.8,<4.0
Classifier: License :: OSI Approved :: GNU General Public License v2 (GPLv2)
Classifier: Programming Language :: Python :: 3
Classifier: Programming Language :: Python :: 3.8
Classifier: Programming Language :: Python :: 3.9
Classifier: Programming Language :: Python :: 3.10
Classifier: Programming Language :: Python :: 3.11
Classifier: Programming Language :: Python :: 3.12
Requires-Dist: aws_authenticator (>=2.0.0,<3.0.0)
Requires-Dist: aws_crawler (>=1.2.4,<2.0.0)
Requires-Dist: boto3 (>=1.16.0,<2.0.0)
Requires-Dist: multithreader (>=1.0.4,<2.0.0)
Project-URL: Repository, https://gitlab.com/fer1035_python/modules/pypi-aws_administrator
